{
  "browser_state_0A": "🔗  Opened new tab with https://www.inkers.ai\n\nInteractive Elements:\n{\n  \"success\": true,\n  \"nav\": [\n    {\n      \"id\": 1,\n      \"desc\": \"Home\",\n      \"action\": \"click_element_by_index\"\n    },\n    {\n      \"id\": 2,\n      \"desc\": \"About\",\n      \"action\": \"click_element_by_index\"\n    },\n    {\n      \"id\": 5,\n      \"desc\": \"Team\",\n      \"action\": \"click_element_by_index\"\n    },\n    {\n      \"id\": 6,\n      \"desc\": \"Pricing\",\n      \"action\": \"click_element_by_index\"\n    },\n    {\n      \"id\": 7,\n      \"desc\": \"Contact\",\n      \"action\": \"click_element_by_index\"\n    },\n    {\n      \"id\": 8,\n      \"desc\": \"Demo\",\n      \"action\": \"click_element_by_index\"\n    },\n    {\n      \"id\": 10,\n      \"desc\": \"Owners\",\n      \"action\": \"click_element_by_index\"\n    },\n    {\n      \"id\": 11,\n      \"desc\": \"Contractors\",\n      \"action\": \"click_element_by_index\"\n    },\n    {\n      \"id\": 12,\n      \"desc\": \"Architects\",\n      \"action\": \"click_element_by_index\"\n    },\n    {\n      \"id\": 14,\n      \"desc\": \"Request a demo (cta-demo-button)\",\n      \"action\": \"click_element_by_index\"\n    },\n    {\n      \"id\": 229,\n      \"desc\": \"Link\",\n      \"action\": \"click_element_by_index\"\n    },\n    {\n      \"id\": 231,\n      \"desc\": \"Link\",\n      \"action\": \"click_element_by_index\"\n    },\n    {\n      \"id\": 233,\n      \"desc\": \"Link\",\n      \"action\": \"click_element_by_index\"\n    },\n    {\n      \"id\": 301,\n      \"desc\": \"Contact\",\n      \"action\": \"click_element_by_index\"\n    },\n    {\n      \"id\": 302,\n      \"desc\": \"Terms of Use\",\n      \"action\": \"click_element_by_index\"\n    },\n    {\n      \"id\": 303,\n      \"desc\": \"About\",\n      \"action\": \"click_element_by_index\"\n    }\n  ],\n  \"forms\": [\n    {\n      \"id\": 261,\n      \"desc\": \"Enter your first name (Name_First)\",\n      \"action\": \"input_text\"\n    },\n    {\n      \"id\": 263,\n      \"desc\": \"Enter your last name (Name_Last)\",\n      \"action\": \"input_text\"\n    },\n    {\n      \"id\": 265,\n      \"desc\": \"Enter country code (PhoneNumber_countrycodeval)\",\n      \"action\": \"input_text\"\n    },\n    {\n      \"id\": 267,\n      \"desc\": \"Enter your phone number (PhoneNumber_countrycode)\",\n      \"action\": \"input_text\"\n    },\n    {\n      \"id\": 269,\n      \"desc\": \"Enter your organization name (SingleLine1)\",\n      \"action\": \"input_text\"\n    },\n    {\n      \"id\": 271,\n      \"desc\": \"Enter your email (Email)\",\n      \"action\": \"input_text\"\n    },\n    {\n      \"id\": 273,\n      \"desc\": \"Enter area to scan (sqft) (Number)\",\n      \"action\": \"input_text\"\n    },\n    {\n      \"id\": 276,\n      \"desc\": \"Toggle option\",\n      \"action\": \"click_element_by_index\"\n    },\n    {\n      \"id\": 280,\n      \"desc\": \"Toggle option\",\n      \"action\": \"click_element_by_index\"\n    },\n    {\n      \"id\": 283,\n      \"desc\": \"Date Input\",\n      \"action\": \"input_text\"\n    },\n    {\n      \"id\": 285,\n      \"desc\": \"Address Line 1 (Address_AddressLine1)\",\n      \"action\": \"input_text\"\n    },\n    {\n      \"id\": 286,\n      \"desc\": \"Address Line 2 (Address_AddressLine2)\",\n      \"action\": \"input_text\"\n    },\n    {\n      \"id\": 287,\n      \"desc\": \"City (Address_City)\",\n      \"action\": \"input_text\"\n    },\n    {\n      \"id\": 288,\n      \"desc\": \"State/Region/Province (Address_Region)\",\n      \"action\": \"input_text\"\n    },\n    {\n      \"id\": 289,\n      \"desc\": \"Postal / Zip Code (Address_ZipCode)\",\n      \"action\": \"input_text\"\n    },\n    {\n      \"id\": 290,\n      \"desc\": \"Select Address Country (Address_Country)\",\n      \"action\": \"select_dropdown_option\",\n      \"options\": [\n        \"Åland Islands\",\n        \"Afghanistan\",\n        \"Akrotiri\",\n        \"Albania\",\n        \"Algeria\",\n        \"American Samoa\",\n        \"Andorra\",\n        \"Angola\",\n        \"Anguilla\",\n        \"Antarctica\",\n        \"Antigua and Barbuda\",\n        \"Argentina\",\n        \"Armenia\",\n        \"Aruba\",\n        \"Ashmore and Cartier Islands\",\n        \"Australia\",\n        \"Austria\",\n        \"Azerbaijan\",\n        \"Bahrain\",\n        \"Bangladesh\",\n        \"Barbados\",\n        \"Bassas Da India\",\n        \"Belarus\",\n        \"Belgium\",\n        \"Belize\",\n        \"Benin\",\n        \"Bermuda\",\n        \"Bhutan\",\n        \"Bolivia\",\n        \"Bosnia and Herzegovina\",\n        \"Botswana\",\n        \"Bouvet Island\",\n        \"Brazil\",\n        \"British Indian Ocean Territory\",\n        \"British Virgin Islands\",\n        \"Brunei\",\n        \"Bulgaria\",\n        \"Burkina Faso\",\n        \"Burma\",\n        \"Burundi\",\n        \"Cambodia\",\n        \"Cameroon\",\n        \"Canada\",\n        \"Cape Verde\",\n        \"Caribbean Netherlands\",\n        \"Cayman Islands\",\n        \"Central African Republic\",\n        \"Chad\",\n        \"Chile\",\n        \"China\",\n        \"Christmas Island\",\n        \"Clipperton Island\",\n        \"Cocos (Keeling) Islands\",\n        \"Colombia\",\n        \"Comoros\",\n        \"Cook Islands\",\n        \"Coral Sea Islands\",\n        \"Costa Rica\",\n        \"Cote D'Ivoire\",\n        \"Croatia\",\n        \"Cuba\",\n        \"Curaçao\",\n        \"Cyprus\",\n        \"Czech Republic\",\n        \"Democratic Republic of the Congo\",\n        \"Denmark\",\n        \"Dhekelia\",\n        \"Djibouti\",\n        \"Dominica\",\n        \"Dominican Republic\",\n        \"Ecuador\",\n        \"Egypt\",\n        \"El Salvador\",\n        \"Equatorial Guinea\",\n        \"Eritrea\",\n        \"Estonia\",\n        \"Ethiopia\",\n        \"Europa Island\",\n        \"Falkland Islands (Islas Malvinas)\",\n        \"Faroe Islands\",\n        \"Federated States of Micronesia\",\n        \"Fiji\",\n        \"Finland\",\n        \"France\",\n        \"French Guiana\",\n        \"French Polynesia\",\n        \"French Southern and Antarctic Lands\",\n        \"Gabon\",\n        \"Gaza Strip\",\n        \"Georgia\",\n        \"Germany\",\n        \"Ghana\",\n        \"Gibraltar\",\n        \"Glorioso Islands\",\n        \"Greece\",\n        \"Greenland\",\n        \"Grenada\",\n        \"Guadeloupe\",\n        \"Guam\",\n        \"Guatemala\",\n        \"Guernsey\",\n        \"Guinea\",\n        \"Guinea-bissau\",\n        \"Guyana\",\n        \"Haiti\",\n        \"Heard Island and Mcdonald Islands\",\n        \"Holy See (Vatican City)\",\n        \"Honduras\",\n        \"Hong Kong\",\n        \"Hungary\",\n        \"Iceland\",\n        \"India\",\n        \"Indonesia\",\n        \"Iran\",\n        \"Iraq\",\n        \"Ireland\",\n        \"Isle of Man\",\n        \"Israel\",\n        \"Italy\",\n        \"Jamaica\",\n        \"Jan Mayen\",\n        \"Japan\",\n        \"Jersey\",\n        \"Jordan\",\n        \"Juan De Nova Island\",\n        \"Kazakhstan\",\n        \"Kenya\",\n        \"Kiribati\",\n        \"Kosovo\",\n        \"Kuwait\",\n        \"Kyrgyzstan\",\n        \"Laos\",\n        \"Latvia\",\n        \"Lebanon\",\n        \"Lesotho\",\n        \"Liberia\",\n        \"Libya\",\n        \"Liechtenstein\",\n        \"Lithuania\",\n        \"Luxembourg\",\n        \"Macau\",\n        \"Macedonia\",\n        \"Madagascar\",\n        \"Malawi\",\n        \"Malaysia\",\n        \"Maldives\",\n        \"Mali\",\n        \"Malta\",\n        \"Marshall Islands\",\n        \"Martinique\",\n        \"Mauritania\",\n        \"Mauritius\",\n        \"Mayotte\",\n        \"Mexico\",\n        \"Moldova\",\n        \"Monaco\",\n        \"Mongolia\",\n        \"Montenegro\",\n        \"Montserrat\",\n        \"Morocco\",\n        \"Mozambique\",\n        \"Myanmar\",\n        \"Namibia\",\n        \"Nauru\",\n        \"Navassa Island\",\n        \"Nepal\",\n        \"Netherlands Antilles\",\n        \"Netherlands\",\n        \"New Caledonia\",\n        \"New Zealand\",\n        \"Nicaragua\",\n        \"Niger\",\n        \"Nigeria\",\n        \"Niue\",\n        \"Norfolk Island\",\n        \"North Korea\",\n        \"Northern Mariana Islands\",\n        \"Norway\",\n        \"Oman\",\n        \"Pakistan\",\n        \"Palau\",\n        \"Palestine\",\n        \"Panama\",\n        \"Papua New Guinea\",\n        \"Paracel Islands\",\n        \"Paraguay\",\n        \"Peru\",\n        \"Philippines\",\n        \"Pitcairn Islands\",\n        \"Poland\",\n        \"Portugal\",\n        \"Puerto Rico\",\n        \"Qatar\",\n        \"Republic of the Congo\",\n        \"Reunion\",\n        \"Romania\",\n        \"Russia\",\n        \"Rwanda\",\n        \"Saint BarthÃ©lemy\",\n        \"Saint Helena\",\n        \"Saint Kitts and Nevis\",\n        \"Saint Lucia\",\n        \"Saint Martin\",\n        \"Saint Pierre and Miquelon\",\n        \"Saint Vincent and the Grenadines\",\n        \"Samoa\",\n        \"San Marino\",\n        \"Sao Tome and Principe\",\n        \"Saudi Arabia\",\n        \"Senegal\",\n        \"Serbia\",\n        \"Seychelles\",\n        \"Sierra Leone\",\n        \"Singapore\",\n        \"Sint Maarten\",\n        \"Slovakia\",\n        \"Slovenia\",\n        \"Solomon Islands\",\n        \"Somalia\",\n        \"South Africa\",\n        \"South Georgia and the South Sandwich Islands\",\n        \"South Korea\",\n        \"South Sudan\",\n        \"Spain\",\n        \"Spratly Islands\",\n        \"Sri Lanka\",\n        \"Sudan\",\n        \"Suriname\",\n        \"Svalbard\",\n        \"Swaziland\",\n        \"Sweden\",\n        \"Switzerland\",\n        \"Syria\",\n        \"Taiwan\",\n        \"Tajikistan\",\n        \"Tanzania\",\n        \"Thailand\",\n        \"The Bahamas\",\n        \"The Gambia\",\n        \"Timor-leste\",\n        \"Togo\",\n        \"Tokelau\",\n        \"Tonga\",\n        \"Trinidad and Tobago\",\n        \"Tromelin Island\",\n        \"Tunisia\",\n        \"Turkey\",\n        \"Turkmenistan\",\n        \"Turks and Caicos Islands\",\n        \"Tuvalu\",\n        \"Uganda\",\n        \"Ukraine\",\n        \"United Arab Emirates\",\n        \"United Kingdom\",\n        \"United States\",\n        \"Uruguay\",\n        \"Uzbekistan\",\n        \"Vanuatu\",\n        \"Venezuela\",\n        \"Vietnam\",\n        \"Virgin Islands\",\n        \"Wake Island\",\n        \"Wallis and Futuna\",\n        \"West Bank\",\n        \"Western Sahara\",\n        \"Yemen\",\n        \"Zambia\",\n        \"Zimbabwe\"\n      ]\n    },\n    {\n      \"id\": 292,\n      \"desc\": \"Any questions or concerns (MultiLine1)\",\n      \"action\": \"input_text\"\n    },\n    {\n      \"id\": 293,\n      \"desc\": \"Submit\",\n      \"action\": \"click_element_by_index\"\n    },\n    {\n      \"id\": 294,\n      \"desc\": \"Enter your name (name)\",\n      \"action\": \"input_text\"\n    },\n    {\n      \"id\": 295,\n      \"desc\": \"Enter your email (email)\",\n      \"action\": \"input_text\"\n    },\n    {\n      \"id\": 296,\n      \"desc\": \"Subscribe\",\n      \"action\": \"click_element_by_index\"\n    }\n  ],\n  \"buttons\": [\n    {\n      \"id\": 3,\n      \"desc\": \"Product\",\n      \"action\": \"hover item, not implemented yet\"\n    },\n    {\n      \"id\": 4,\n      \"desc\": \"Services\",\n      \"action\": \"hover item, not implemented yet\"\n    },\n    {\n      \"id\": 9,\n      \"desc\": \"Toggle theme\",\n      \"action\": \"click_element_by_index\"\n    },\n    {\n      \"id\": 226,\n      \"desc\": \"Owners & Contractors\",\n      \"action\": \"click_element_by_index\"\n    },\n    {\n      \"id\": 227,\n      \"desc\": \"Architects\",\n      \"action\": \"click_element_by_index\"\n    },\n    {\n      \"id\": 228,\n      \"desc\": \"Lithic Scanner\",\n      \"action\": \"click_element_by_index\"\n    },\n    {\n      \"id\": 230,\n      \"desc\": \"Start Free Trial\",\n      \"action\": \"click_element_by_index\"\n    },\n    {\n      \"id\": 232,\n      \"desc\": \"Start Free Trial\",\n      \"action\": \"click_element_by_index\"\n    },\n    {\n      \"id\": 234,\n      \"desc\": \"Start Free Trial\",\n      \"action\": \"click_element_by_index\"\n    },\n    {\n      \"id\": 259,\n      \"desc\": \"sales@inkers.ai\",\n      \"action\": \"click_element_by_index\"\n    }\n  ],\n  \"total\": 47\n}",
  "click_result_1A": "🖱️  Clicked button with index 8: Demo\n\nInteractive Elements:\n{\n  \"success\": true,\n  \"nav\": [\n    {\n      \"id\": 1,\n      \"desc\": \"Home\",\n      \"action\": \"click_element_by_index\"\n    },\n    {\n      \"id\": 2,\n      \"desc\": \"About\",\n      \"action\": \"click_element_by_index\"\n    },\n    {\n      \"id\": 5,\n      \"desc\": \"Team\",\n      \"action\": \"click_element_by_index\"\n    },\n    {\n      \"id\": 6,\n      \"desc\": \"Pricing\",\n      \"action\": \"click_element_by_index\"\n    },\n    {\n      \"id\": 7,\n      \"desc\": \"Contact\",\n      \"action\": \"click_element_by_index\"\n    },\n    {\n      \"id\": 8,\n      \"desc\": \"Demo\",\n      \"action\": \"click_element_by_index\"\n    },\n    {\n      \"id\": 52,\n      \"desc\": \"Contact\",\n      \"action\": \"click_element_by_index\"\n    },\n    {\n      \"id\": 53,\n      \"desc\": \"Terms of Use\",\n      \"action\": \"click_element_by_index\"\n    },\n    {\n      \"id\": 54,\n      \"desc\": \"About\",\n      \"action\": \"click_element_by_index\"\n    }\n  ],\n  \"forms\": [\n    {\n      \"id\": 12,\n      \"desc\": \"Enter your first name (Name_First)\",\n      \"action\": \"input_text\"\n    },\n    {\n      \"id\": 14,\n      \"desc\": \"Enter your last name (Name_Last)\",\n      \"action\": \"input_text\"\n    },\n    {\n      \"id\": 16,\n      \"desc\": \"Enter country code (PhoneNumber_countrycodeval)\",\n      \"action\": \"input_text\"\n    },\n    {\n      \"id\": 18,\n      \"desc\": \"Enter your phone number (PhoneNumber_countrycode)\",\n      \"action\": \"input_text\"\n    },\n    {\n      \"id\": 20,\n      \"desc\": \"Enter your organization name (SingleLine1)\",\n      \"action\": \"input_text\"\n    },\n    {\n      \"id\": 22,\n      \"desc\": \"Enter your email (Email)\",\n      \"action\": \"input_text\"\n    },\n    {\n      \"id\": 24,\n      \"desc\": \"Enter area to scan (sqft) (Number)\",\n      \"action\": \"input_text\"\n    },\n    {\n      \"id\": 27,\n      \"desc\": \"Toggle option\",\n      \"action\": \"click_element_by_index\"\n    },\n    {\n      \"id\": 31,\n      \"desc\": \"Toggle option\",\n      \"action\": \"click_element_by_index\"\n    },\n    {\n      \"id\": 34,\n      \"desc\": \"Date Input\",\n      \"action\": \"input_text\"\n    },\n    {\n      \"id\": 36,\n      \"desc\": \"Address Line 1 (Address_AddressLine1)\",\n      \"action\": \"input_text\"\n    },\n    {\n      \"id\": 37,\n      \"desc\": \"Address Line 2 (Address_AddressLine2)\",\n      \"action\": \"input_text\"\n    },\n    {\n      \"id\": 38,\n      \"desc\": \"City (Address_City)\",\n      \"action\": \"input_text\"\n    },\n    {\n      \"id\": 39,\n      \"desc\": \"State/Region/Province (Address_Region)\",\n      \"action\": \"input_text\"\n    },\n    {\n      \"id\": 40,\n      \"desc\": \"Postal / Zip Code (Address_ZipCode)\",\n      \"action\": \"input_text\"\n    },\n    {\n      \"id\": 41,\n      \"desc\": \"Select Address Country (Address_Country)\",\n      \"action\": \"select_dropdown_option\",\n      \"options\": [\n        \"Åland Islands\",\n        \"Afghanistan\",\n        \"Akrotiri\",\n        \"Albania\",\n        \"Algeria\",\n        \"American Samoa\",\n        \"Andorra\",\n        \"Angola\",\n        \"Anguilla\",\n        \"Antarctica\",\n        \"Antigua and Barbuda\",\n        \"Argentina\",\n        \"Armenia\",\n        \"Aruba\",\n        \"Ashmore and Cartier Islands\",\n        \"Australia\",\n        \"Austria\",\n        \"Azerbaijan\",\n        \"Bahrain\",\n        \"Bangladesh\",\n        \"Barbados\",\n        \"Bassas Da India\",\n        \"Belarus\",\n        \"Belgium\",\n        \"Belize\",\n        \"Benin\",\n        \"Bermuda\",\n        \"Bhutan\",\n        \"Bolivia\",\n        \"Bosnia and Herzegovina\",\n        \"Botswana\",\n        \"Bouvet Island\",\n        \"Brazil\",\n        \"British Indian Ocean Territory\",\n        \"British Virgin Islands\",\n        \"Brunei\",\n        \"Bulgaria\",\n        \"Burkina Faso\",\n        \"Burma\",\n        \"Burundi\",\n        \"Cambodia\",\n        \"Cameroon\",\n        \"Canada\",\n        \"Cape Verde\",\n        \"Caribbean Netherlands\",\n        \"Cayman Islands\",\n        \"Central African Republic\",\n        \"Chad\",\n        \"Chile\",\n        \"China\",\n        \"Christmas Island\",\n        \"Clipperton Island\",\n        \"Cocos (Keeling) Islands\",\n        \"Colombia\",\n        \"Comoros\",\n        \"Cook Islands\",\n        \"Coral Sea Islands\",\n        \"Costa Rica\",\n        \"Cote D'Ivoire\",\n        \"Croatia\",\n        \"Cuba\",\n        \"Curaçao\",\n        \"Cyprus\",\n        \"Czech Republic\",\n        \"Democratic Republic of the Congo\",\n        \"Denmark\",\n        \"Dhekelia\",\n        \"Djibouti\",\n        \"Dominica\",\n        \"Dominican Republic\",\n        \"Ecuador\",\n        \"Egypt\",\n        \"El Salvador\",\n        \"Equatorial Guinea\",\n        \"Eritrea\",\n        \"Estonia\",\n        \"Ethiopia\",\n        \"Europa Island\",\n        \"Falkland Islands (Islas Malvinas)\",\n        \"Faroe Islands\",\n        \"Federated States of Micronesia\",\n        \"Fiji\",\n        \"Finland\",\n        \"France\",\n        \"French Guiana\",\n        \"French Polynesia\",\n        \"French Southern and Antarctic Lands\",\n        \"Gabon\",\n        \"Gaza Strip\",\n        \"Georgia\",\n        \"Germany\",\n        \"Ghana\",\n        \"Gibraltar\",\n        \"Glorioso Islands\",\n        \"Greece\",\n        \"Greenland\",\n        \"Grenada\",\n        \"Guadeloupe\",\n        \"Guam\",\n        \"Guatemala\",\n        \"Guernsey\",\n        \"Guinea\",\n        \"Guinea-bissau\",\n        \"Guyana\",\n        \"Haiti\",\n        \"Heard Island and Mcdonald Islands\",\n        \"Holy See (Vatican City)\",\n        \"Honduras\",\n        \"Hong Kong\",\n        \"Hungary\",\n        \"Iceland\",\n        \"India\",\n        \"Indonesia\",\n        \"Iran\",\n        \"Iraq\",\n        \"Ireland\",\n        \"Isle of Man\",\n        \"Israel\",\n        \"Italy\",\n        \"Jamaica\",\n        \"Jan Mayen\",\n        \"Japan\",\n        \"Jersey\",\n        \"Jordan\",\n        \"Juan De Nova Island\",\n        \"Kazakhstan\",\n        \"Kenya\",\n        \"Kiribati\",\n        \"Kosovo\",\n        \"Kuwait\",\n        \"Kyrgyzstan\",\n        \"Laos\",\n        \"Latvia\",\n        \"Lebanon\",\n        \"Lesotho\",\n        \"Liberia\",\n        \"Libya\",\n        \"Liechtenstein\",\n        \"Lithuania\",\n        \"Luxembourg\",\n        \"Macau\",\n        \"Macedonia\",\n        \"Madagascar\",\n        \"Malawi\",\n        \"Malaysia\",\n        \"Maldives\",\n        \"Mali\",\n        \"Malta\",\n        \"Marshall Islands\",\n        \"Martinique\",\n        \"Mauritania\",\n        \"Mauritius\",\n        \"Mayotte\",\n        \"Mexico\",\n        \"Moldova\",\n        \"Monaco\",\n        \"Mongolia\",\n        \"Montenegro\",\n        \"Montserrat\",\n        \"Morocco\",\n        \"Mozambique\",\n        \"Myanmar\",\n        \"Namibia\",\n        \"Nauru\",\n        \"Navassa Island\",\n        \"Nepal\",\n        \"Netherlands Antilles\",\n        \"Netherlands\",\n        \"New Caledonia\",\n        \"New Zealand\",\n        \"Nicaragua\",\n        \"Niger\",\n        \"Nigeria\",\n        \"Niue\",\n        \"Norfolk Island\",\n        \"North Korea\",\n        \"Northern Mariana Islands\",\n        \"Norway\",\n        \"Oman\",\n        \"Pakistan\",\n        \"Palau\",\n        \"Palestine\",\n        \"Panama\",\n        \"Papua New Guinea\",\n        \"Paracel Islands\",\n        \"Paraguay\",\n        \"Peru\",\n        \"Philippines\",\n        \"Pitcairn Islands\",\n        \"Poland\",\n        \"Portugal\",\n        \"Puerto Rico\",\n        \"Qatar\",\n        \"Republic of the Congo\",\n        \"Reunion\",\n        \"Romania\",\n        \"Russia\",\n        \"Rwanda\",\n        \"Saint BarthÃ©lemy\",\n        \"Saint Helena\",\n        \"Saint Kitts and Nevis\",\n        \"Saint Lucia\",\n        \"Saint Martin\",\n        \"Saint Pierre and Miquelon\",\n        \"Saint Vincent and the Grenadines\",\n        \"Samoa\",\n        \"San Marino\",\n        \"Sao Tome and Principe\",\n        \"Saudi Arabia\",\n        \"Senegal\",\n        \"Serbia\",\n        \"Seychelles\",\n        \"Sierra Leone\",\n        \"Singapore\",\n        \"Sint Maarten\",\n        \"Slovakia\",\n        \"Slovenia\",\n        \"Solomon Islands\",\n        \"Somalia\",\n        \"South Africa\",\n        \"South Georgia and the South Sandwich Islands\",\n        \"South Korea\",\n        \"South Sudan\",\n        \"Spain\",\n        \"Spratly Islands\",\n        \"Sri Lanka\",\n        \"Sudan\",\n        \"Suriname\",\n        \"Svalbard\",\n        \"Swaziland\",\n        \"Sweden\",\n        \"Switzerland\",\n        \"Syria\",\n        \"Taiwan\",\n        \"Tajikistan\",\n        \"Tanzania\",\n        \"Thailand\",\n        \"The Bahamas\",\n        \"The Gambia\",\n        \"Timor-leste\",\n        \"Togo\",\n        \"Tokelau\",\n        \"Tonga\",\n        \"Trinidad and Tobago\",\n        \"Tromelin Island\",\n        \"Tunisia\",\n        \"Turkey\",\n        \"Turkmenistan\",\n        \"Turks and Caicos Islands\",\n        \"Tuvalu\",\n        \"Uganda\",\n        \"Ukraine\",\n        \"United Arab Emirates\",\n        \"United Kingdom\",\n        \"United States\",\n        \"Uruguay\",\n        \"Uzbekistan\",\n        \"Vanuatu\",\n        \"Venezuela\",\n        \"Vietnam\",\n        \"Virgin Islands\",\n        \"Wake Island\",\n        \"Wallis and Futuna\",\n        \"West Bank\",\n        \"Western Sahara\",\n        \"Yemen\",\n        \"Zambia\",\n        \"Zimbabwe\"\n      ]\n    },\n    {\n      \"id\": 43,\n      \"desc\": \"Any questions or concerns (MultiLine1)\",\n      \"action\": \"input_text\"\n    },\n    {\n      \"id\": 44,\n      \"desc\": \"Submit\",\n      \"action\": \"click_element_by_index\"\n    },\n    {\n      \"id\": 45,\n      \"desc\": \"Enter your name (name)\",\n      \"action\": \"input_text\"\n    },\n    {\n      \"id\": 46,\n      \"desc\": \"Enter your email (email)\",\n      \"action\": \"input_text\"\n    },\n    {\n      \"id\": 47,\n      \"desc\": \"Subscribe\",\n      \"action\": \"click_element_by_index\"\n    }\n  ],\n  \"buttons\": [\n    {\n      \"id\": 3,\n      \"desc\": \"Product\",\n      \"action\": \"hover item, not implemented yet\"\n    },\n    {\n      \"id\": 4,\n      \"desc\": \"Services\",\n      \"action\": \"hover item, not implemented yet\"\n    },\n    {\n      \"id\": 9,\n      \"desc\": \"Toggle theme\",\n      \"action\": \"click_element_by_index\"\n    },\n    {\n      \"id\": 10,\n      \"desc\": \"sales@inkers.ai\",\n      \"action\": \"click_element_by_index\"\n    },\n    {\n      \"id\": 55,\n      \"desc\": \"Contact Us | AI Solutions for Your Construction Business (__next-route-announcer__)\",\n      \"action\": \"click_element_by_index\"\n    }\n  ],\n  \"total\": 35\n}",
  "browser_state_1A": {
    "page_structure": {
      "total_interactive_elements": 35,
      "categories": {
        "navigation": 9,
        "forms": 21,
        "buttons": 5
      }
    },
    "content": [
      {
        "type": "interactive",
        "element_type": "button",
        "id": 55,
        "text": "Contact Us | AI Solutions for Your Construction Business (__next-route-announcer__)",
        "action": "click_element_by_index",
        "category": "button"
      },
      {
        "type": "text",
        "content": "[logo]"
      },
      {
        "type": "interactive",
        "element_type": "nav_link",
        "id": 1,
        "text": "Home",
        "action": "click_element_by_index",
        "category": "navigation"
      },
      {
        "type": "interactive",
        "element_type": "nav_link",
        "id": 2,
        "text": "About",
        "action": "click_element_by_index",
        "category": "navigation"
      },
      {
        "type": "interactive",
        "element_type": "button",
        "id": 3,
        "text": "Product",
        "action": "hover item, not implemented yet",
        "category": "button"
      },
      {
        "type": "interactive",
        "element_type": "button",
        "id": 4,
        "text": "Services",
        "action": "hover item, not implemented yet",
        "category": "button"
      },
      {
        "type": "interactive",
        "element_type": "nav_link",
        "id": 5,
        "text": "Team",
        "action": "click_element_by_index",
        "category": "navigation"
      },
      {
        "type": "interactive",
        "element_type": "nav_link",
        "id": 6,
        "text": "Pricing",
        "action": "click_element_by_index",
        "category": "navigation"
      },
      {
        "type": "interactive",
        "element_type": "nav_link",
        "id": 7,
        "text": "Contact",
        "action": "click_element_by_index",
        "category": "navigation"
      },
      {
        "type": "interactive",
        "element_type": "nav_link",
        "id": 8,
        "text": "Demo",
        "action": "click_element_by_index",
        "category": "navigation"
      },
      {
        "type": "interactive",
        "element_type": "button",
        "id": 9,
        "text": "Toggle theme",
        "action": "click_element_by_index",
        "category": "button"
      },
      {
        "type": "interactive",
        "element_type": "nav_link",
        "id": 52,
        "text": "Contact",
        "action": "click_element_by_index",
        "category": "navigation"
      },
      {
        "type": "paragraph",
        "content": "Get in touch for advanced AI solutions for your construction project"
      },
      {
        "type": "heading",
        "level": 2,
        "content": "Interested in a Free Scan?"
      },
      {
        "type": "text",
        "content": "For sales inquiries, please contact:"
      },
      {
        "type": "interactive",
        "element_type": "button",
        "id": 10,
        "text": "sales@inkers.ai",
        "action": "click_element_by_index",
        "category": "button"
      },
      {
        "type": "paragraph",
        "content": "Fill out the form below, and we'll process your request to schedule your complimentary scan at a convenient time!"
      },
      {
        "type": "heading",
        "level": 2,
        "content": "Contact Information"
      },
      {
        "type": "text",
        "content": "Phone Number"
      },
      {
        "type": "interactive",
        "element_type": "text_input",
        "id": 20,
        "text": "Enter your organization name (SingleLine1)",
        "action": "input_text",
        "category": "form"
      },
      {
        "type": "text",
        "content": "Organization Name *"
      },
      {
        "type": "text",
        "content": "Area to Scan (sqft)"
      },
      {
        "type": "text",
        "content": "Area to Scan (sqft) *"
      },
      {
        "type": "text",
        "content": "Is BIM Available?"
      },
      {
        "type": "text",
        "content": "Is Project Schedule Available?"
      },
      {
        "type": "text",
        "content": "Preferred Demo Date"
      },
      {
        "type": "text",
        "content": "Show date picker"
      },
      {
        "type": "text",
        "content": "Will be formatted as dd-MMM-yyyy"
      },
      {
        "type": "heading",
        "level": 2,
        "content": "Project Details"
      },
      {
        "type": "heading",
        "level": 2,
        "content": "Additional Information"
      },
      {
        "type": "heading",
        "level": 2,
        "content": "Project Address"
      },
      {
        "type": "text",
        "content": "Project Address"
      },
      {
        "type": "text",
        "content": "Project Address *"
      },
      {
        "type": "interactive",
        "element_type": "text_input",
        "id": 37,
        "text": "Address Line 2 (Address_AddressLine2)",
        "action": "input_text",
        "category": "form"
      },
      {
        "type": "interactive",
        "element_type": "text_input",
        "id": 38,
        "text": "City (Address_City)",
        "action": "input_text",
        "category": "form"
      },
      {
        "type": "interactive",
        "element_type": "text_input",
        "id": 39,
        "text": "State/Region/Province (Address_Region)",
        "action": "input_text",
        "category": "form"
      },
      {
        "type": "interactive",
        "element_type": "text_input",
        "id": 40,
        "text": "Postal / Zip Code (Address_ZipCode)",
        "action": "input_text",
        "category": "form"
      },
      {
        "type": "text",
        "content": "Antigua and Barbuda"
      },
      {
        "type": "text",
        "content": "Ashmore and Cartier Islands"
      },
      {
        "type": "text",
        "content": "Bosnia and Herzegovina"
      },
      {
        "type": "text",
        "content": "British Indian Ocean Territory"
      },
      {
        "type": "text",
        "content": "British Virgin Islands"
      },
      {
        "type": "text",
        "content": "Caribbean Netherlands"
      },
      {
        "type": "text",
        "content": "Central African Republic"
      },
      {
        "type": "text",
        "content": "Christmas Island"
      },
      {
        "type": "text",
        "content": "Clipperton Island"
      },
      {
        "type": "text",
        "content": "Cocos (Keeling) Islands"
      },
      {
        "type": "text",
        "content": "Coral Sea Islands"
      },
      {
        "type": "text",
        "content": "Democratic Republic of the Congo"
      },
      {
        "type": "text",
        "content": "Dominican Republic"
      },
      {
        "type": "text",
        "content": "Equatorial Guinea"
      },
      {
        "type": "text",
        "content": "Falkland Islands (Islas Malvinas)"
      },
      {
        "type": "text",
        "content": "Federated States of Micronesia"
      },
      {
        "type": "text",
        "content": "French Polynesia"
      },
      {
        "type": "text",
        "content": "French Southern and Antarctic Lands"
      },
      {
        "type": "text",
        "content": "Glorioso Islands"
      },
      {
        "type": "text",
        "content": "Heard Island and Mcdonald Islands"
      },
      {
        "type": "text",
        "content": "Holy See (Vatican City)"
      },
      {
        "type": "text",
        "content": "Juan De Nova Island"
      },
      {
        "type": "text",
        "content": "Marshall Islands"
      },
      {
        "type": "text",
        "content": "Netherlands Antilles"
      },
      {
        "type": "text",
        "content": "Northern Mariana Islands"
      },
      {
        "type": "text",
        "content": "Papua New Guinea"
      },
      {
        "type": "text",
        "content": "Pitcairn Islands"
      },
      {
        "type": "text",
        "content": "Republic of the Congo"
      },
      {
        "type": "text",
        "content": "Saint BarthÃ©lemy"
      },
      {
        "type": "text",
        "content": "Saint Kitts and Nevis"
      },
      {
        "type": "text",
        "content": "Saint Pierre and Miquelon"
      },
      {
        "type": "text",
        "content": "Saint Vincent and the Grenadines"
      },
      {
        "type": "text",
        "content": "Sao Tome and Principe"
      },
      {
        "type": "text",
        "content": "South Georgia and the South Sandwich Islands"
      },
      {
        "type": "text",
        "content": "Trinidad and Tobago"
      },
      {
        "type": "text",
        "content": "Turks and Caicos Islands"
      },
      {
        "type": "text",
        "content": "United Arab Emirates"
      },
      {
        "type": "text",
        "content": "Wallis and Futuna"
      },
      {
        "type": "interactive",
        "element_type": "text_input",
        "id": 43,
        "text": "Any questions or concerns (MultiLine1)",
        "action": "input_text",
        "category": "form"
      },
      {
        "type": "text",
        "content": "Any questions or concerns you have?"
      },
      {
        "type": "interactive",
        "element_type": "text_input",
        "id": 44,
        "text": "Submit",
        "action": "click_element_by_index",
        "category": "form"
      },
      {
        "type": "heading",
        "level": 2,
        "content": "Stay Updated with Monthly Insights"
      },
      {
        "type": "paragraph",
        "content": "Get exclusive monthly updates delivered straight to your inbox."
      },
      {
        "type": "interactive",
        "element_type": "text_input",
        "id": 45,
        "text": "Enter your name (name)",
        "action": "input_text",
        "category": "form"
      },
      {
        "type": "interactive",
        "element_type": "email_input",
        "id": 22,
        "text": "Enter your email (Email)",
        "action": "input_text",
        "category": "form"
      },
      {
        "type": "interactive",
        "element_type": "text_input",
        "id": 47,
        "text": "Subscribe",
        "action": "click_element_by_index",
        "category": "form"
      },
      {
        "type": "text",
        "content": "Unsubscribe anytime, no strings attached!"
      },
      {
        "type": "heading",
        "level": 2,
        "content": "Inkers Technology Pvt Ltd"
      },
      {
        "type": "text",
        "content": "India Office"
      },
      {
        "type": "text",
        "content": "The Work Address - Vaishnavi HSR"
      },
      {
        "type": "text",
        "content": "Layout, Bengaluru, Karnataka 560102"
      },
      {
        "type": "text",
        "content": "8 The Green, Ste A"
      },
      {
        "type": "text",
        "content": "Dover, Kent County"
      },
      {
        "type": "text",
        "content": "19901, Delaware"
      },
      {
        "type": "text",
        "content": "[social-link]"
      },
      {
        "type": "heading",
        "level": 2,
        "content": "Useful Links"
      },
      {
        "type": "text",
        "content": "[Contact]"
      },
      {
        "type": "interactive",
        "element_type": "nav_link",
        "id": 53,
        "text": "Terms of Use",
        "action": "click_element_by_index",
        "category": "navigation"
      },
      {
        "type": "interactive",
        "element_type": "nav_link",
        "id": 54,
        "text": "About",
        "action": "click_element_by_index",
        "category": "navigation"
      },
      {
        "type": "paragraph",
        "content": "© 2025 Inkers Technology Pvt Ltd. All rights reserved."
      },
      {
        "type": "paragraph",
        "content": "Contact Us | AI Solutions for Your Construction Business"
      },
      {
        "type": "section",
        "content": "Additional Interactive Elements",
        "level": 2
      },
      {
        "type": "interactive",
        "element_type": "text_input",
        "id": 12,
        "text": "Enter your first name (Name_First)",
        "action": "input_text",
        "category": "form"
      },
      {
        "type": "interactive",
        "element_type": "text_input",
        "id": 14,
        "text": "Enter your last name (Name_Last)",
        "action": "input_text",
        "category": "form"
      },
      {
        "type": "interactive",
        "element_type": "phone_input",
        "id": 16,
        "text": "Enter country code (PhoneNumber_countrycodeval)",
        "action": "input_text",
        "category": "form"
      },
      {
        "type": "interactive",
        "element_type": "phone_input",
        "id": 18,
        "text": "Enter your phone number (PhoneNumber_countrycode)",
        "action": "input_text",
        "category": "form"
      },
      {
        "type": "interactive",
        "element_type": "number_input",
        "id": 24,
        "text": "Enter area to scan (sqft) (Number)",
        "action": "input_text",
        "category": "form"
      },
      {
        "type": "interactive",
        "element_type": "checkbox",
        "id": 27,
        "text": "Toggle option",
        "action": "click_element_by_index",
        "category": "form"
      },
      {
        "type": "interactive",
        "element_type": "checkbox",
        "id": 31,
        "text": "Toggle option",
        "action": "click_element_by_index",
        "category": "form"
      },
      {
        "type": "interactive",
        "element_type": "date_input",
        "id": 34,
        "text": "Date Input",
        "action": "input_text",
        "category": "form"
      },
      {
        "type": "interactive",
        "element_type": "text_input",
        "id": 36,
        "text": "Address Line 1 (Address_AddressLine1)",
        "action": "input_text",
        "category": "form"
      },
      {
        "type": "interactive",
        "element_type": "dropdown",
        "id": 41,
        "text": "Select Address Country (Address_Country)",
        "action": "select_dropdown_option",
        "category": "form",
        "options_count": 268,
        "has_options": true,
        "sample_options": [
          "Åland Islands",
          "Afghanistan",
          "Akrotiri",
          "Albania",
          "Algeria"
        ]
      },
      {
        "type": "interactive",
        "element_type": "email_input",
        "id": 46,
        "text": "Enter your email (email)",
        "action": "input_text",
        "category": "form"
      }
    ]
  }
}